trifectadb/__init__.py
trifectadb/base.py
trifectadb-4.0.1.dist-info/METADATA
trifectadb-4.0.1.dist-info/WHEEL
trifectadb-4.0.1.dist-info/top_level.txt
trifectadb-4.0.1.dist-info/RECORD
