Metadata-Version: 2.1
Name: trifectadb
Version: 4.0.1
Summary: TrifectaDB - A Multiplatform, Multilanguage Database Solution
Author: Ojas Gupta
Author-email: dev.i7apps@gmail.com
Requires-Dist: requests
